odoo/addons/stock_picking_volume/README.rst
odoo/addons/stock_picking_volume/__init__.py
odoo/addons/stock_picking_volume/__manifest__.py
odoo/addons/stock_picking_volume/hooks.py
odoo/addons/stock_picking_volume/i18n/it.po
odoo/addons/stock_picking_volume/i18n/stock_picking_volume.pot
odoo/addons/stock_picking_volume/models/__init__.py
odoo/addons/stock_picking_volume/models/product_product.py
odoo/addons/stock_picking_volume/models/stock_move.py
odoo/addons/stock_picking_volume/models/stock_picking.py
odoo/addons/stock_picking_volume/readme/CONTRIBUTORS.rst
odoo/addons/stock_picking_volume/readme/CREDITS.rst
odoo/addons/stock_picking_volume/readme/DESCRIPTION.rst
odoo/addons/stock_picking_volume/readme/USAGE.rst
odoo/addons/stock_picking_volume/static/description/icon.png
odoo/addons/stock_picking_volume/static/description/index.html
odoo/addons/stock_picking_volume/tests/__init__.py
odoo/addons/stock_picking_volume/tests/test_stock_picking_volume.py
odoo/addons/stock_picking_volume/views/stock_move.xml
odoo/addons/stock_picking_volume/views/stock_picking.xml
odoo14_addon_stock_picking_volume-14.0.1.1.1.dist-info/METADATA
odoo14_addon_stock_picking_volume-14.0.1.1.1.dist-info/WHEEL
odoo14_addon_stock_picking_volume-14.0.1.1.1.dist-info/top_level.txt
odoo14_addon_stock_picking_volume-14.0.1.1.1.dist-info/RECORD
