Metadata-Version: 2.1
Name: odoo14-addon-stock_picking_volume
Version: 14.0.1.1.1
Summary: Compute volume information on stock moves and pickings
Home-page: https://github.com/OCA/stock-logistics-warehouse
Author: ACSONE SA/NV,Odoo Community Association (OCA)
Author-email: support@odoo-community.org
License: AGPL-3
Classifier: Programming Language :: Python
Classifier: Framework :: Odoo
Classifier: Framework :: Odoo :: 14.0
Classifier: License :: OSI Approved :: GNU Affero General Public License v3
Classifier: Development Status :: 4 - Beta
Requires-Python: >=3.6
Requires-Dist: odoo14-addon-product-dimension
Requires-Dist: odoo <14.1dev,>=14.0a
